sanic_cache/__init__.py
sanic_cache/base.py
sanic_cache/redis.py
sanic_cache/serializers.py
sanic_cache-0.1.1.dist-info/METADATA
sanic_cache-0.1.1.dist-info/WHEEL
sanic_cache-0.1.1.dist-info/top_level.txt
sanic_cache-0.1.1.dist-info/RECORD
