Metadata-Version: 2.1
Name: sanic-cache
Version: 0.1.1
Summary: flask-cache -> sanic-cache
Home-page: https://github.com/nahongyan1997/sanic_cache
Author: Na haha
Author-email: 547840062@qq.com
License: MIT
Requires-Dist: sanic >=23.12.1
Requires-Dist: sanic-ext
Requires-Dist: redis >=5.0.0
